qwinq-0.1.0.dist-info/METADATA
qwinq-0.1.0.dist-info/WHEEL
qwinq/__init__.py
qwinq/py.typed
qwinq/qwinq.pyi
qwinq/qwinq.cpython-312-darwin.so
qwinq-0.1.0.dist-info/RECORD
