Metadata-Version: 2.3
Name: qwinq
Version: 0.1.0
Classifier: Programming Language :: Rust
Classifier: Programming Language :: Python :: Implementation :: CPython
Classifier: Programming Language :: Python :: Implementation :: PyPy
Requires-Dist: qfetch ==0.1
Requires-Dist: qdata ==0.1
Requires-Dist: qstrategy ==0.1
Summary: 股票个人量化交易通用模块
Keywords: quantitative trading,stock,rust,automatic trading
Author-email: buf1024 <buf1024@gmail.com>
Maintainer-email: buf1024 <buf1024@gmail.com>
Requires-Python: >=3.7
